nonebridge/__init__.py
nonebridge-0.1.5.dist-info/LICENSE
nonebridge-0.1.5.dist-info/METADATA
nonebridge-0.1.5.dist-info/WHEEL
nonebridge-0.1.5.dist-info/RECORD
