Metadata-Version: 2.1
Name: nonebridge
Version: 0.1.5
Summary: A adapter event bridge for nonebot2 makes plugins run on different adapters without any modify
Home-page: https://github.com/ColdThunder11/nonebot-adapter-telegram
License: MIT
Keywords: bot
Author: ColdThunder11
Author-email: lslyj27761@gmail.com
Requires-Python: >=3.8.1,<4.0.0
Classifier: License :: OSI Approved :: MIT License
Classifier: Operating System :: OS Independent
Classifier: Programming Language :: Python :: 3
Classifier: Programming Language :: Python :: 3.9
Classifier: Programming Language :: Python :: 3.10
Classifier: Programming Language :: Python :: 3.11
Requires-Dist: nonebot-adapter-antelegram (>=0.2.0-dev10,<0.3.0)
Requires-Dist: nonebot-adapter-onebot (>=2.2.0,<3.0.0)
Requires-Dist: nonebot2 (>=2.0.0rc2,<3.0.0)
Project-URL: Repository, https://github.com/ColdThunder11/nonebot-adapter-telegram
